{
  "HALProvider": {
    "Other Devices": {
      "window": {
        "visible": false
      }
    }
  },
  "NTProvider": {
    "types": {
      "/FMSInfo": "FMSInfo",
      "/LiveWindow/Ungrouped/DigitalInput[0]": "Digital Input",
      "/LiveWindow/Ungrouped/DigitalInput[1]": "Digital Input",
      "/LiveWindow/Ungrouped/DigitalInput[2]": "Digital Input",
      "/LiveWindow/Ungrouped/DigitalInput[3]": "Digital Input",
      "/LiveWindow/Ungrouped/PIDController[1]": "PIDController",
      "/LiveWindow/Ungrouped/PIDController[2]": "PIDController",
      "/LiveWindow/Ungrouped/PIDController[3]": "PIDController",
      "/LiveWindow/Ungrouped/PIDController[4]": "PIDController",
      "/LiveWindow/Ungrouped/Scheduler": "Scheduler",
      "/LiveWindow/Ungrouped/Spark[0]": "Motor Controller",
      "/LiveWindow/Ungrouped/navX-Sensor[4]": "Gyro",
      "/SmartDashboard/Calibrate": "Command",
      "/SmartDashboard/Field": "Field2d"
    },
    "windows": {
      "/SmartDashboard/Field": {
        "window": {
          "visible": true
        }
      }
    }
  },
  "NetworkTables": {
    "persistent": {
      "Preferences": {
        "open": true
      }
    },
    "transitory": {
      "SmartDashboard": {
        "Field": {
          "open": true
        },
        "open": true
      }
    }
  }
}
